MySBdt/MySBdt.py
MySBdt/__init__.py
mysoftbank/__init__.py
mysoftbank/mysoftbank.py
mysb_reminder-5.1.dist-info/METADATA
mysb_reminder-5.1.dist-info/WHEEL
mysb_reminder-5.1.dist-info/top_level.txt
mysb_reminder-5.1.dist-info/RECORD
