Metadata-Version: 2.1
Name: mysb-reminder
Version: 5.1
Summary: Remaining data notifications with LINE Notify
Home-page: https://github.com/miya/mysb-reminder
Author: miya
Author-email: m0zurillex@gmail.com
License: UNKNOWN
Keywords: softbank,scraping,LINE Notify
Platform: UNKNOWN
Requires-Dist: lxml
Requires-Dist: requests
Requires-Dist: beautifulsoup4
